Workbook
Name Customer: Customerdata[Cust_Id]
Name hsncode: vendorsdata[HSN Code]

Sheet Dashboard
R14: Notification !!
R16: =Inventory!L11 -> 📞 Laptop HP xyz i5 Need To Re-order !! Ph 9812xxxxxx
R17: =Inventory!L12 -> 📞 Wireless Printer Need To Re-order !! Ph 9812xxxxxx
R18: =Inventory!L13 -> 📞 Desktop Need To Re-order !! Ph 9813xxxxxx
R21: =Inventory!L16 -> 📞 Camera Need To Re-order !! Ph 9813xxxxxx
R22: =Inventory!L17 -> 📞 Headphones Need To Re-order !! Ph 9814xxxxxx
R23: =Inventory!L18
R24: =Inventory!L19

Sheet Customers
D8: Cust_Id | E8: Name | F8: Email | G8: Address
D9: 100 | E9: Rahul | F9: Rahul@gmail.com | G9: Delhi, India
D10: 101 | E10: Vikas | F10: Rahul@gmail.com | G10: 121102, Palwal, HR
D11: 102 | E11: Arun | F11: Rahul@gmail.com | G11: Faridabad, 121101
D12: 103 | E12: Vansh | F12: Rahul@gmail.com | G12: Agra, UP
D13: 104 | E13: Sahil | F13: Rahul@gmail.com | G13: New Delhi, 110011
D14: 105 | E14: Lovelesh | F14: Rahul@gmail.com | G14: Gurgaon, Sec-15
D15: 106 | E15: Sachin | F15: Rahul@gmail.com | G15: Chandigarh,sector-17
D16: 107 | E16: haslly | F16: hally@hmail.com | G16: yfykfkyud

Sheet Products
D9: HSN Code | E9: Product Name | F9: Cost | G9: Selling Price
D10: N1001 | E10: Smart Watch | F10: 980 | G10: 1176
D11: N1002 | E11: Laptop HP xyz i5 | F11: 34500 | G11: 41400
D12: N1003 | E12: Wireless Printer | F12: 4600 | G12: 5520
D13: N1004 | E13: Desktop | F13: 21000 | G13: 25200
D14: N1005 | E14: Mouse | F14: 200 | G14: 240
D15: N1006 | E15: Rgb Keyboard | F15: 340 | G15: 408
D16: N1007 | E16: Camera | F16: 52000 | G16: 62400
D17: N1008 | E17: Headphones | F17: 799 | G17: 958.8
D18: N1009 | E18: Speakers | F18: 670 | G18: 804
D19: N1010 | E19: Tablets | F19: 23500 | G19: 28200

Sheet Vendors
D9: HSN Code | E9: Product Name | F9: Vendor Name | G9: Phone | H9: Address
D10: N1001 | E10: Smart Watch | F10: Tech99 | G10: 9812xxxxxx | H10: Faridabad, 121101
D11: N1002 | E11: Laptop HP xyz i5 | F11: Tech99 | G11: 9812xxxxxx | H11: Faridabad, 121102
D12: N1003 | E12: Wireless Printer | F12: Tech99 | G12: 9812xxxxxx | H12: Faridabad, 121103
D13: N1004 | E13: Desktop | F13: GG Traders | G13: 9813xxxxxx | H13: Gurgaon, Sec-15
D14: N1005 | E14: Mouse | F14: GG Traders | G14: 9813xxxxxx | H14: Gurgaon, Sec-16
D15: N1006 | E15: Rgb Keyboard | F15: GG Traders | G15: 9813xxxxxx | H15: Gurgaon, Sec-17
D16: N1007 | E16: Camera | F16: GG Traders | G16: 9813xxxxxx | H16: Gurgaon, Sec-18
D17: N1008 | E17: Headphones | F17: Compac | G17: 9814xxxxxx | H17: New Delhi, 110012
D18: N1009 | E18: Speakers | F18: Compac | G18: 9814xxxxxx | H18: New Delhi, 110013
D19: N1010 | E19: Tablets | F19: Compac | G19: 9814xxxxxx | H19: New Delhi, 110014

Sheet New Entry
E11: Purchase Entry
E14: Sales Entry

Sheet Purchase
D9: HSN Code | E9: Product Name | F9: Vendor | G9: Date | H9: Units | I9: Cost | J9: Amount
D10: N1001 | E10: =IFERROR(VLOOKUP(Table5[[#This Row],[HSN Code]],productdata[#All],2,0),"") -> Smart Watch | F10: =IFERROR(VLOOKUP(Table5[[#This Row],[HSN Code]],vendorsdata[#All],3,0),"") -> Tech99 | G10: 46036 | H10: 10 | I10: =IFERROR(VLOOKUP(Table5[[#This Row],[HSN Code]],productdata[#All],3,0),"") -> 980 | J10: =IFERROR(Table5[[#This Row],[Units]]*Table5[[#This Row],[Cost]],"") -> 9800
D11: N1002 | E11: =IFERROR(VLOOKUP(Table5[[#This Row],[HSN Code]],productdata[#All],2,0),"") -> Laptop HP xyz i5 | F11: =IFERROR(VLOOKUP(Table5[[#This Row],[HSN Code]],vendorsdata[#All],3,0),"") -> Tech99 | H11: 13 | I11: =IFERROR(VLOOKUP(Table5[[#This Row],[HSN Code]],productdata[#All],3,0),"") -> 34500 | J11: =IFERROR(Table5[[#This Row],[Units]]*Table5[[#This Row],[Cost]],"") -> 448500
D12: N1003 | E12: =IFERROR(VLOOKUP(Table5[[#This Row],[HSN Code]],productdata[#All],2,0),"") -> Wireless Printer | F12: =IFERROR(VLOOKUP(Table5[[#This Row],[HSN Code]],vendorsdata[#All],3,0),"") -> Tech99 | H12: 20 | I12: =IFERROR(VLOOKUP(Table5[[#This Row],[HSN Code]],productdata[#All],3,0),"") -> 4600 | J12: =IFERROR(Table5[[#This Row],[Units]]*Table5[[#This Row],[Cost]],"") -> 92000
D13: N1004 | E13: =IFERROR(VLOOKUP(Table5[[#This Row],[HSN Code]],productdata[#All],2,0),"") -> Desktop | F13: =IFERROR(VLOOKUP(Table5[[#This Row],[HSN Code]],vendorsdata[#All],3,0),"") -> GG Traders | H13: 5 | I13: =IFERROR(VLOOKUP(Table5[[#This Row],[HSN Code]],productdata[#All],3,0),"") -> 21000 | J13: =IFERROR(Table5[[#This Row],[Units]]*Table5[[#This Row],[Cost]],"") -> 105000
D14: N1005 | E14: =IFERROR(VLOOKUP(Table5[[#This Row],[HSN Code]],productdata[#All],2,0),"") -> Mouse | F14: =IFERROR(VLOOKUP(Table5[[#This Row],[HSN Code]],vendorsdata[#All],3,0),"") -> GG Traders | H14: 7 | I14: =IFERROR(VLOOKUP(Table5[[#This Row],[HSN Code]],productdata[#All],3,0),"") -> 200 | J14: =IFERROR(Table5[[#This Row],[Units]]*Table5[[#This Row],[Cost]],"") -> 1400
D15: N1006 | E15: =IFERROR(VLOOKUP(Table5[[#This Row],[HSN Code]],productdata[#All],2,0),"") -> Rgb Keyboard | F15: =IFERROR(VLOOKUP(Table5[[#This Row],[HSN Code]],vendorsdata[#All],3,0),"") -> GG Traders | H15: 8 | I15: =IFERROR(VLOOKUP(Table5[[#This Row],[HSN Code]],productdata[#All],3,0),"") -> 340 | J15: =IFERROR(Table5[[#This Row],[Units]]*Table5[[#This Row],[Cost]],"") -> 2720
D16: N1007 | E16: =IFERROR(VLOOKUP(Table5[[#This Row],[HSN Code]],productdata[#All],2,0),"") -> Camera | F16: =IFERROR(VLOOKUP(Table5[[#This Row],[HSN Code]],vendorsdata[#All],3,0),"") -> GG Traders | H16: 5 | I16: =IFERROR(VLOOKUP(Table5[[#This Row],[HSN Code]],productdata[#All],3,0),"") -> 52000 | J16: =IFERROR(Table5[[#This Row],[Units]]*Table5[[#This Row],[Cost]],"") -> 260000
D17: N1008 | E17: =IFERROR(VLOOKUP(Table5[[#This Row],[HSN Code]],productdata[#All],2,0),"") -> Headphones | F17: =IFERROR(VLOOKUP(Table5[[#This Row],[HSN Code]],vendorsdata[#All],3,0),"") -> Compac | H17: 3 | I17: =IFERROR(VLOOKUP(Table5[[#This Row],[HSN Code]],productdata[#All],3,0),"") -> 799 | J17: =IFERROR(Table5[[#This Row],[Units]]*Table5[[#This Row],[Cost]],"") -> 2397
D18: N1009 | E18: =IFERROR(VLOOKUP(Table5[[#This Row],[HSN Code]],productdata[#All],2,0),"") -> Speakers | F18: =IFERROR(VLOOKUP(Table5[[#This Row],[HSN Code]],vendorsdata[#All],3,0),"") -> Compac | H18: 21 | I18: =IFERROR(VLOOKUP(Table5[[#This Row],[HSN Code]],productdata[#All],3,0),"") -> 670 | J18: =IFERROR(Table5[[#This Row],[Units]]*Table5[[#This Row],[Cost]],"") -> 14070
D19: N1010 | E19: =IFERROR(VLOOKUP(Table5[[#This Row],[HSN Code]],productdata[#All],2,0),"") -> Tablets | F19: =IFERROR(VLOOKUP(Table5[[#This Row],[HSN Code]],vendorsdata[#All],3,0),"") -> Compac | H19: 60 | I19: =IFERROR(VLOOKUP(Table5[[#This Row],[HSN Code]],productdata[#All],3,0),"") -> 23500 | J19: =IFERROR(Table5[[#This Row],[Units]]*Table5[[#This Row],[Cost]],"") -> 1410000
D20: N1001 | E20: =IFERROR(VLOOKUP(Table5[[#This Row],[HSN Code]],productdata[#All],2,0),"") -> Smart Watch | F20: =IFERROR(VLOOKUP(Table5[[#This Row],[HSN Code]],vendorsdata[#All],3,0),"") -> Tech99 | H20: 20 | I20: =IFERROR(VLOOKUP(Table5[[#This Row],[HSN Code]],productdata[#All],3,0),"") -> 980 | J20: =IFERROR(Table5[[#This Row],[Units]]*Table5[[#This Row],[Cost]],"") -> 19600
D21: N1005 | E21: =IFERROR(VLOOKUP(Table5[[#This Row],[HSN Code]],productdata[#All],2,0),"") -> Mouse | F21: =IFERROR(VLOOKUP(Table5[[#This Row],[HSN Code]],vendorsdata[#All],3,0),"") -> GG Traders | H21: 50 | I21: =IFERROR(VLOOKUP(Table5[[#This Row],[HSN Code]],productdata[#All],3,0),"") -> 200 | J21: =IFERROR(Table5[[#This Row],[Units]]*Table5[[#This Row],[Cost]],"") -> 10000
D22: N1007 | E22: =IFERROR(VLOOKUP(Table5[[#This Row],[HSN Code]],productdata[#All],2,0),"") -> Camera | F22: =IFERROR(VLOOKUP(Table5[[#This Row],[HSN Code]],vendorsdata[#All],3,0),"") -> GG Traders | G22: 46328 | H22: 10 | I22: =IFERROR(VLOOKUP(Table5[[#This Row],[HSN Code]],productdata[#All],3,0),"") -> 52000 | J22: =IFERROR(Table5[[#This Row],[Units]]*Table5[[#This Row],[Cost]],"") -> 520000
E23: =IFERROR(VLOOKUP(Table5[[#This Row],[HSN Code]],productdata[#All],2,0),"") | F23: =IFERROR(VLOOKUP(Table5[[#This Row],[HSN Code]],vendorsdata[#All],3,0),"") | I23: =IFERROR(VLOOKUP(Table5[[#This Row],[HSN Code]],productdata[#All],3,0),"") | J23: =IFERROR(Table5[[#This Row],[Units]]*Table5[[#This Row],[Cost]],"")

Sheet Sales
D9: Cust_ID | E9: Cust_Name | F9: HSN Code | G9: Product Name | H9: Date | I9: Stock(Units) | J9: Units | K9: Price | L9: Amount
D10: 100 | E10: =IFERROR(VLOOKUP(Table7[[#This Row],[Cust_ID]],Customerdata[#All],2,0),"") -> Rahul | F10: N1001 | G10: =IFERROR(VLOOKUP(Table7[[#This Row],[HSN Code]],productdata[#All],2,0),"") -> Smart Watch | I10: =IFERROR(VLOOKUP(Table7[[#This Row],[HSN Code]],Table8[#All],6,0),"") -> 21 | J10: 9 | K10: =IFERROR(VLOOKUP(Table7[[#This Row],[HSN Code]],productdata[#All],4,0),"") -> 1176 | L10: =IFERROR(Table7[[#This Row],[Price]]*Table7[[#This Row],[Units]],"") -> 10584
D11: 101 | E11: =IFERROR(VLOOKUP(Table7[[#This Row],[Cust_ID]],Customerdata[#All],2,0),"") -> Vikas | F11: N1002 | G11: =IFERROR(VLOOKUP(Table7[[#This Row],[HSN Code]],productdata[#All],2,0),"") -> Laptop HP xyz i5 | I11: =IFERROR(VLOOKUP(Table7[[#This Row],[HSN Code]],Table8[#All],6,0),"") -> 3 | J11: 10 | K11: =IFERROR(VLOOKUP(Table7[[#This Row],[HSN Code]],productdata[#All],4,0),"") -> 41400 | L11: =IFERROR(Table7[[#This Row],[Price]]*Table7[[#This Row],[Units]],"") -> 414000
D12: 103 | E12: =IFERROR(VLOOKUP(Table7[[#This Row],[Cust_ID]],Customerdata[#All],2,0),"") -> Vansh | F12: N1003 | G12: =IFERROR(VLOOKUP(Table7[[#This Row],[HSN Code]],productdata[#All],2,0),"") -> Wireless Printer | I12: =IFERROR(VLOOKUP(Table7[[#This Row],[HSN Code]],Table8[#All],6,0),"") -> 1 | J12: 19 | K12: =IFERROR(VLOOKUP(Table7[[#This Row],[HSN Code]],productdata[#All],4,0),"") -> 5520 | L12: =IFERROR(Table7[[#This Row],[Price]]*Table7[[#This Row],[Units]],"") -> 104880
D13: 104 | E13: =IFERROR(VLOOKUP(Table7[[#This Row],[Cust_ID]],Customerdata[#All],2,0),"") -> Sahil | F13: N1004 | G13: =IFERROR(VLOOKUP(Table7[[#This Row],[HSN Code]],productdata[#All],2,0),"") -> Desktop | I13: =IFERROR(VLOOKUP(Table7[[#This Row],[HSN Code]],Table8[#All],6,0),"") -> -1 | J13: 6 | K13: =IFERROR(VLOOKUP(Table7[[#This Row],[HSN Code]],productdata[#All],4,0),"") -> 25200 | L13: =IFERROR(Table7[[#This Row],[Price]]*Table7[[#This Row],[Units]],"") -> 151200
D14: 105 | E14: =IFERROR(VLOOKUP(Table7[[#This Row],[Cust_ID]],Customerdata[#All],2,0),"") -> Lovelesh | F14: N1005 | G14: =IFERROR(VLOOKUP(Table7[[#This Row],[HSN Code]],productdata[#All],2,0),"") -> Mouse | I14: =IFERROR(VLOOKUP(Table7[[#This Row],[HSN Code]],Table8[#All],6,0),"") -> 40 | J14: 7 | K14: =IFERROR(VLOOKUP(Table7[[#This Row],[HSN Code]],productdata[#All],4,0),"") -> 240 | L14: =IFERROR(Table7[[#This Row],[Price]]*Table7[[#This Row],[Units]],"") -> 1680
D15: 106 | E15: =IFERROR(VLOOKUP(Table7[[#This Row],[Cust_ID]],Customerdata[#All],2,0),"") -> Sachin | F15: N1006 | G15: =IFERROR(VLOOKUP(Table7[[#This Row],[HSN Code]],productdata[#All],2,0),"") -> Rgb Keyboard | I15: =IFERROR(VLOOKUP(Table7[[#This Row],[HSN Code]],Table8[#All],6,0),"") -> 6 | J15: 2 | K15: =IFERROR(VLOOKUP(Table7[[#This Row],[HSN Code]],productdata[#All],4,0),"") -> 408 | L15: =IFERROR(Table7[[#This Row],[Price]]*Table7[[#This Row],[Units]],"") -> 816
D16: 100 | E16: =IFERROR(VLOOKUP(Table7[[#This Row],[Cust_ID]],Customerdata[#All],2,0),"") -> Rahul | F16: N1007 | G16: =IFERROR(VLOOKUP(Table7[[#This Row],[HSN Code]],productdata[#All],2,0),"") -> Camera | I16: =IFERROR(VLOOKUP(Table7[[#This Row],[HSN Code]],Table8[#All],6,0),"") -> 2 | J16: 3 | K16: =IFERROR(VLOOKUP(Table7[[#This Row],[HSN Code]],productdata[#All],4,0),"") -> 62400 | L16: =IFERROR(Table7[[#This Row],[Price]]*Table7[[#This Row],[Units]],"") -> 187200
D17: 103 | E17: =IFERROR(VLOOKUP(Table7[[#This Row],[Cust_ID]],Customerdata[#All],2,0),"") -> Vansh | F17: N1007 | G17: =IFERROR(VLOOKUP(Table7[[#This Row],[HSN Code]],productdata[#All],2,0),"") -> Camera | I17: =IFERROR(VLOOKUP(Table7[[#This Row],[HSN Code]],Table8[#All],6,0),"") -> 2 | J17: 10 | K17: =IFERROR(VLOOKUP(Table7[[#This Row],[HSN Code]],productdata[#All],4,0),"") -> 62400 | L17: =IFERROR(Table7[[#This Row],[Price]]*Table7[[#This Row],[Units]],"") -> 624000
D18: 101 | E18: =IFERROR(VLOOKUP(Table7[[#This Row],[Cust_ID]],Customerdata[#All],2,0),"") -> Vikas | F18: N1005 | G18: =IFERROR(VLOOKUP(Table7[[#This Row],[HSN Code]],productdata[#All],2,0),"") -> Mouse | I18: =IFERROR(VLOOKUP(Table7[[#This Row],[HSN Code]],Table8[#All],6,0),"") -> 40 | J18: 10 | K18: =IFERROR(VLOOKUP(Table7[[#This Row],[HSN Code]],productdata[#All],4,0),"") -> 240 | L18: =IFERROR(Table7[[#This Row],[Price]]*Table7[[#This Row],[Units]],"") -> 2400
E20: =IFERROR(VLOOKUP(Table7[[#This Row],[Cust_ID]],Customerdata[#All],2,0),"") | G20: =IFERROR(VLOOKUP(Table7[[#This Row],[HSN Code]],productdata[#All],2,0),"") | I20: =IFERROR(VLOOKUP(Table7[[#This Row],[HSN Code]],Table8[#All],6,0),"") | K20: =IFERROR(VLOOKUP(Table7[[#This Row],[HSN Code]],productdata[#All],4,0),"") | L20: =IFERROR(Table7[[#This Row],[Price]]*Table7[[#This Row],[Units]],"")
E21: =IFERROR(VLOOKUP(Table7[[#This Row],[Cust_ID]],Customerdata[#All],2,0),"") | G21: =IFERROR(VLOOKUP(Table7[[#This Row],[HSN Code]],productdata[#All],2,0),"") | I21: =IFERROR(VLOOKUP(Table7[[#This Row],[HSN Code]],Table8[#All],6,0),"") | K21: =IFERROR(VLOOKUP(Table7[[#This Row],[HSN Code]],productdata[#All],4,0),"") | L21: =IFERROR(Table7[[#This Row],[Price]]*Table7[[#This Row],[Units]],"")
E22: =IFERROR(VLOOKUP(Table7[[#This Row],[Cust_ID]],Customerdata[#All],2,0),"") | G22: =IFERROR(VLOOKUP(Table7[[#This Row],[HSN Code]],productdata[#All],2,0),"") | I22: =IFERROR(VLOOKUP(Table7[[#This Row],[HSN Code]],Table8[#All],6,0),"") | K22: =IFERROR(VLOOKUP(Table7[[#This Row],[HSN Code]],productdata[#All],4,0),"") | L22: =IFERROR(Table7[[#This Row],[Price]]*Table7[[#This Row],[Units]],"")

Sheet Inventory
D9: HSN Code | E9: Product Name | F9: Cost | G9: P Units | H9: S Units | I9: Stock | J9: Stock Amt. | K9: Staus | L9: Notification
D10: =productdata[[#This Row],[HSN Code]] -> N1001 | E10: =productdata[[#This Row],[Product Name]] -> Smart Watch | F10: =productdata[[#This Row],[Cost]] -> 980 | G10: =SUMIF(Table5[Product Name],Table8[Product Name],Table5[Units]) -> 30 | H10: =SUMIF(Table7[Product Name],Table8[Product Name],Table7[Units]) -> 9 | I10: =Table8[[#This Row],[P Units]]-Table8[[#This Row],[S Units]] -> 21 | J10: =Table8[[#This Row],[Cost]]*Table8[[#This Row],[Stock]] -> 20580 | K10: =IF(Table8[[#This Row],[Stock]]>0,"In Stock","Out Of Stock") -> In Stock | L10: =IFERROR(IF(Table8[[#This Row],[Stock]]<5," 📞 "& Table8[[#This Row],[Product Name]] &" Need To Re-order !! Ph " &IFERROR(VLOOKUP(Table8[[#This Row],[HSN Code]],vendorsdata[#All],4,0),""),""),"")
D11: =productdata[[#This Row],[HSN Code]] -> N1002 | E11: =productdata[[#This Row],[Product Name]] -> Laptop HP xyz i5 | F11: =productdata[[#This Row],[Cost]] -> 34500 | G11: =SUMIF(Table5[Product Name],Table8[Product Name],Table5[Units]) -> 13 | H11: =SUMIF(Table7[Product Name],Table8[Product Name],Table7[Units]) -> 10 | I11: =Table8[[#This Row],[P Units]]-Table8[[#This Row],[S Units]] -> 3 | J11: =Table8[[#This Row],[Cost]]*Table8[[#This Row],[Stock]] -> 103500 | K11: =IF(Table8[[#This Row],[Stock]]>0,"In Stock","Out Of Stock") -> In Stock | L11: =IFERROR(IF(Table8[[#This Row],[Stock]]<5," 📞 "& Table8[[#This Row],[Product Name]] &" Need To Re-order !! Ph " &IFERROR(VLOOKUP(Table8[[#This Row],[HSN Code]],vendorsdata[#All],4,0),""),""),"") -> 📞 Laptop HP xyz i5 Need To Re-order !! Ph 9812xxxxxx
D12: =productdata[[#This Row],[HSN Code]] -> N1003 | E12: =productdata[[#This Row],[Product Name]] -> Wireless Printer | F12: =productdata[[#This Row],[Cost]] -> 4600 | G12: =SUMIF(Table5[Product Name],Table8[Product Name],Table5[Units]) -> 20 | H12: =SUMIF(Table7[Product Name],Table8[Product Name],Table7[Units]) -> 19 | I12: =Table8[[#This Row],[P Units]]-Table8[[#This Row],[S Units]] -> 1 | J12: =Table8[[#This Row],[Cost]]*Table8[[#This Row],[Stock]] -> 4600 | K12: =IF(Table8[[#This Row],[Stock]]>0,"In Stock","Out Of Stock") -> In Stock | L12: =IFERROR(IF(Table8[[#This Row],[Stock]]<5," 📞 "& Table8[[#This Row],[Product Name]] &" Need To Re-order !! Ph " &IFERROR(VLOOKUP(Table8[[#This Row],[HSN Code]],vendorsdata[#All],4,0),""),""),"") -> 📞 Wireless Printer Need To Re-order !! Ph 9812xxxxxx
D13: =productdata[[#This Row],[HSN Code]] -> N1004 | E13: =productdata[[#This Row],[Product Name]] -> Desktop | F13: =productdata[[#This Row],[Cost]] -> 21000 | G13: =SUMIF(Table5[Product Name],Table8[Product Name],Table5[Units]) -> 5 | H13: =SUMIF(Table7[Product Name],Table8[Product Name],Table7[Units]) -> 6 | I13: =Table8[[#This Row],[P Units]]-Table8[[#This Row],[S Units]] -> -1 | J13: =Table8[[#This Row],[Cost]]*Table8[[#This Row],[Stock]] -> -21000 | K13: =IF(Table8[[#This Row],[Stock]]>0,"In Stock","Out Of Stock") -> Out Of Stock | L13: =IFERROR(IF(Table8[[#This Row],[Stock]]<5," 📞 "& Table8[[#This Row],[Product Name]] &" Need To Re-order !! Ph " &IFERROR(VLOOKUP(Table8[[#This Row],[HSN Code]],vendorsdata[#All],4,0),""),""),"") -> 📞 Desktop Need To Re-order !! Ph 9813xxxxxx
D14: =productdata[[#This Row],[HSN Code]] -> N1005 | E14: =productdata[[#This Row],[Product Name]] -> Mouse | F14: =productdata[[#This Row],[Cost]] -> 200 | G14: =SUMIF(Table5[Product Name],Table8[Product Name],Table5[Units]) -> 57 | H14: =SUMIF(Table7[Product Name],Table8[Product Name],Table7[Units]) -> 17 | I14: =Table8[[#This Row],[P Units]]-Table8[[#This Row],[S Units]] -> 40 | J14: =Table8[[#This Row],[Cost]]*Table8[[#This Row],[Stock]] -> 8000 | K14: =IF(Table8[[#This Row],[Stock]]>0,"In Stock","Out Of Stock") -> In Stock | L14: =IFERROR(IF(Table8[[#This Row],[Stock]]<5," 📞 "& Table8[[#This Row],[Product Name]] &" Need To Re-order !! Ph " &IFERROR(VLOOKUP(Table8[[#This Row],[HSN Code]],vendorsdata[#All],4,0),""),""),"")
D15: =productdata[[#This Row],[HSN Code]] -> N1006 | E15: =productdata[[#This Row],[Product Name]] -> Rgb Keyboard | F15: =productdata[[#This Row],[Cost]] -> 340 | G15: =SUMIF(Table5[Product Name],Table8[Product Name],Table5[Units]) -> 8 | H15: =SUMIF(Table7[Product Name],Table8[Product Name],Table7[Units]) -> 2 | I15: =Table8[[#This Row],[P Units]]-Table8[[#This Row],[S Units]] -> 6 | J15: =Table8[[#This Row],[Cost]]*Table8[[#This Row],[Stock]] -> 2040 | K15: =IF(Table8[[#This Row],[Stock]]>0,"In Stock","Out Of Stock") -> In Stock | L15: =IFERROR(IF(Table8[[#This Row],[Stock]]<5," 📞 "& Table8[[#This Row],[Product Name]] &" Need To Re-order !! Ph " &IFERROR(VLOOKUP(Table8[[#This Row],[HSN Code]],vendorsdata[#All],4,0),""),""),"")
D16: =productdata[[#This Row],[HSN Code]] -> N1007 | E16: =productdata[[#This Row],[Product Name]] -> Camera | F16: =productdata[[#This Row],[Cost]] -> 52000 | G16: =SUMIF(Table5[Product Name],Table8[Product Name],Table5[Units]) -> 15 | H16: =SUMIF(Table7[Product Name],Table8[Product Name],Table7[Units]) -> 13 | I16: =Table8[[#This Row],[P Units]]-Table8[[#This Row],[S Units]] -> 2 | J16: =Table8[[#This Row],[Cost]]*Table8[[#This Row],[Stock]] -> 104000 | K16: =IF(Table8[[#This Row],[Stock]]>0,"In Stock","Out Of Stock") -> In Stock | L16: =IFERROR(IF(Table8[[#This Row],[Stock]]<5," 📞 "& Table8[[#This Row],[Product Name]] &" Need To Re-order !! Ph " &IFERROR(VLOOKUP(Table8[[#This Row],[HSN Code]],vendorsdata[#All],4,0),""),""),"") -> 📞 Camera Need To Re-order !! Ph 9813xxxxxx
D17: =productdata[[#This Row],[HSN Code]] -> N1008 | E17: =productdata[[#This Row],[Product Name]] -> Headphones | F17: =productdata[[#This Row],[Cost]] -> 799 | G17: =SUMIF(Table5[Product Name],Table8[Product Name],Table5[Units]) -> 3 | H17: =SUMIF(Table7[Product Name],Table8[Product Name],Table7[Units]) -> 0 | I17: =Table8[[#This Row],[P Units]]-Table8[[#This Row],[S Units]] -> 3 | J17: =Table8[[#This Row],[Cost]]*Table8[[#This Row],[Stock]] -> 2397 | K17: =IF(Table8[[#This Row],[Stock]]>0,"In Stock","Out Of Stock") -> In Stock | L17: =IFERROR(IF(Table8[[#This Row],[Stock]]<5," 📞 "& Table8[[#This Row],[Product Name]] &" Need To Re-order !! Ph " &IFERROR(VLOOKUP(Table8[[#This Row],[HSN Code]],vendorsdata[#All],4,0),""),""),"") -> 📞 Headphones Need To Re-order !! Ph 9814xxxxxx
D18: =productdata[[#This Row],[HSN Code]] -> N1009 | E18: =productdata[[#This Row],[Product Name]] -> Speakers | F18: =productdata[[#This Row],[Cost]] -> 670 | G18: =SUMIF(Table5[Product Name],Table8[Product Name],Table5[Units]) -> 21 | H18: =SUMIF(Table7[Product Name],Table8[Product Name],Table7[Units]) -> 0 | I18: =Table8[[#This Row],[P Units]]-Table8[[#This Row],[S Units]] -> 21 | J18: =Table8[[#This Row],[Cost]]*Table8[[#This Row],[Stock]] -> 14070 | K18: =IF(Table8[[#This Row],[Stock]]>0,"In Stock","Out Of Stock") -> In Stock | L18: =IFERROR(IF(Table8[[#This Row],[Stock]]<5," 📞 "& Table8[[#This Row],[Product Name]] &" Need To Re-order !! Ph " &IFERROR(VLOOKUP(Table8[[#This Row],[HSN Code]],vendorsdata[#All],4,0),""),""),"")
D19: =productdata[[#This Row],[HSN Code]] -> N1010 | E19: =productdata[[#This Row],[Product Name]] -> Tablets | F19: =productdata[[#This Row],[Cost]] -> 23500 | G19: =SUMIF(Table5[Product Name],Table8[Product Name],Table5[Units]) -> 60 | H19: =SUMIF(Table7[Product Name],Table8[Product Name],Table7[Units]) -> 0 | I19: =Table8[[#This Row],[P Units]]-Table8[[#This Row],[S Units]] -> 60 | J19: =Table8[[#This Row],[Cost]]*Table8[[#This Row],[Stock]] -> 1410000 | K19: =IF(Table8[[#This Row],[Stock]]>0,"In Stock","Out Of Stock") -> In Stock | L19: =IFERROR(IF(Table8[[#This Row],[Stock]]<5," 📞 "& Table8[[#This Row],[Product Name]] &" Need To Re-order !! Ph " &IFERROR(VLOOKUP(Table8[[#This Row],[HSN Code]],vendorsdata[#All],4,0),""),""),"")

Sheet Pivot
H3: Row Labels | I3: Sum of S Units
B4: Count of Cust_Id | D4: Total customer | H4: Wireless Printer | I4: 19
B5: 8 | D5: =GETPIVOTDATA("Cust_Id",$B$4) -> 8 | H5: Mouse | I5: 17
H6: Camera | I6: 13
H7: Laptop HP xyz i5 | I7: 10
B8: Count of Product Name | D8: Total Product | H8: Smart Watch | I8: 9
B9: 10 | D9: =GETPIVOTDATA("Product Name",$B$8) -> 10 | H9: Grand Total | I9: 68
F11: Profit./Loss
B12: Sum of Amount | D12: Total Purchase | F12: =D16+D26-D13 -> 249460
B13: 2895487 | D13: =GETPIVOTDATA("Amount",$B$12) -> 2895487 | H13: Row Labels | I13: Sum of Amount
H14: Vansh | I14: 728880
B15: Sum of Amount | D15: Total Sales | H15: Vikas | I15: 416400
B16: 1496760 | D16: =GETPIVOTDATA("Amount",$B$15) -> 1496760 | H16: Rahul | I16: 197784
H17: Sahil | I17: 151200
H18: Lovelesh | I18: 1680
H19: Grand Total | I19: 1495944
B20: Sum of Stock | D20: IN STOCK
B21: 156 | D21: =GETPIVOTDATA("Stock",$B$20) -> 156
B25: Sum of Stock Amt. | D25: Stock Amount
B26: 1648187 | D26: =GETPIVOTDATA("Stock Amt.",$B$25) -> 1648187

Sheet Sheet9
